openpack/__init__.py
openpack/basepack.py
openpack/editor.py
openpack/officepack.py
openpack/part-edit.py
openpack/py.typed
openpack/util.py
openpack/zip-listdir.py
openpack/zippack.py
openpack-2.4.2.dist-info/METADATA
openpack-2.4.2.dist-info/WHEEL
openpack-2.4.2.dist-info/entry_points.txt
openpack-2.4.2.dist-info/top_level.txt
openpack-2.4.2.dist-info/RECORD
